dv_flow/libide/__ext__.py
dv_flow/libide/__init__.py
dv_flow/libide/dvt_flow.dv
dv_flow/libide/dvt_update_filelist.py
dv_flow/libide/flow.dv
dv_flow/libide/vbl_flow.dv
dv_flow/libide/vbl_update_filelist.py
dv_flow_libide-0.0.214956629056rc0.dist-info/licenses/LICENSE
dv_flow_libide-0.0.214956629056rc0.dist-info/METADATA
dv_flow_libide-0.0.214956629056rc0.dist-info/WHEEL
dv_flow_libide-0.0.214956629056rc0.dist-info/entry_points.txt
dv_flow_libide-0.0.214956629056rc0.dist-info/top_level.txt
dv_flow_libide-0.0.214956629056rc0.dist-info/RECORD
