Metadata-Version: 2.4
Name: dv-flow-libide
Version: 0.0.214956629056rc0
Summary: Provides dv-flow tasks for maintaining IDE-integration files
Author-email: Matthew Ballance <matt.ballance@gmail.com>
License:                                  Apache License
License-File: LICENSE
Requires-Dist: dv-flow-mgr
Dynamic: license-file
